secure_password/__init__.py
secure_password/__main__.py
secure_password/generator.py
secure_password/validator.py
tests/__init__.py
tests/test_generator.py
tests/test_validator.py
SafePassGen-1.0.6.dist-info/LICENSE
SafePassGen-1.0.6.dist-info/METADATA
SafePassGen-1.0.6.dist-info/WHEEL
SafePassGen-1.0.6.dist-info/entry_points.txt
SafePassGen-1.0.6.dist-info/top_level.txt
SafePassGen-1.0.6.dist-info/RECORD
