Metadata-Version: 2.1
Name: SafePassGen
Version: 1.0.6
Summary: A package to generate secure passwords with customizable options and check vulnerability and strength
Home-page: https://github.com/diegoamengarelli/passgenesis
Author: Diego Mengarelli
Classifier: Programming Language :: Python :: 3
Classifier: License :: OSI Approved :: MIT License
Classifier: Operating System :: OS Independent
Classifier: Topic :: Software Development :: Libraries :: Python Modules
Requires-Python: >=3.9
License-File: LICENSE
